setup.py
MegaMess_server.egg-info/PKG-INFO
MegaMess_server.egg-info/SOURCES.txt
MegaMess_server.egg-info/dependency_links.txt
MegaMess_server.egg-info/requires.txt
MegaMess_server.egg-info/top_level.txt
server/__init__.py
server/database_server.py
server/server_main.py
server/common/__init__.py
server/common/decos.py
server/common/descriptors.py
server/common/errors.py
server/common/metaclasses.py
server/common/utils.py
server/common/variables.py
server/gui_server/__init__.py
server/gui_server/gui_main_window.py
server/gui_server/gui_registration_user.py
server/gui_server/gui_settings_window.py
server/gui_server/user_registration_config.py
server/logs/__init__.py
server/logs/server_log_config.py
server/logs/files_log/__init__.py